oauthlib_extras/__init__.py
oauthlib_extras/oauth2/__init__.py
oauthlib_extras/oauth2/extras/__init__.py
oauthlib_extras/oauth2/extras/errors.py
oauthlib_extras/oauth2/extras/parameters.py
oauthlib_extras/oauth2/extras/clients/__init__.py
oauthlib_extras/oauth2/extras/clients/web_application_push.py
oauthlib_extras/oauth2/extras/endpoints/__init__.py
oauthlib_extras/oauth2/extras/endpoints/pre_configured.py
oauthlib_extras/oauth2/extras/grant_types/__init__.py
oauthlib_extras/oauth2/extras/grant_types/authorization_code_push.py
oauthlib_extras-1.0.1.dist-info/METADATA
oauthlib_extras-1.0.1.dist-info/RECORD
oauthlib_extras-1.0.1.dist-info/WHEEL
oauthlib_extras-1.0.1.dist-info/top_level.txt
