Metadata-Version: 2.1
Name: oauthlib-extras
Version: 1.0.1
Summary: Extends the oauthlib package with additional grant types
Home-page: https://github.com/Innoactive/oauthlib-extras
Author: Amar Cutura
Author-email: amar.cutura@innoactive.de
License: MIT
Keywords: oauth,oauthlib,grant
Platform: any
Requires-Dist: oauthlib (==1.1.2)
